nclick/__init__.py
nclick/version.py
nclick/eda/__init__.py
nclick/eda/summarize.py
nclick/excel/__init__.py
nclick/excel/cell_styles.py
nclick/excel/writing_tools.py
nclick/model/__init__.py
nclick/model/categorical_encoder.py
nclick/model/cv.py
nclick/model/gbdt.py
nclick/model/imputer.py
nclick/model/mlp.py
nclick/model/scaler.py
nclick/model/util.py
nclick/utils/__init__.py
nclick/utils/io.py
nclick/utils/log.py
nclick-0.0.1.dist-info/METADATA
nclick-0.0.1.dist-info/WHEEL
nclick-0.0.1.dist-info/top_level.txt
nclick-0.0.1.dist-info/RECORD
