Metadata-Version: 2.1
Name: nclick
Version: 0.0.1
Summary: Code for Laziness.
Home-page: UNKNOWN
Author: copypaste
Author-email: UNKNOWN
License: MIT
Platform: UNKNOWN
Requires-Dist: matplotlib
Requires-Dist: numpy
Requires-Dist: pandas
Requires-Dist: sklearn
Requires-Dist: tqdm
Requires-Dist: openpyxl
Requires-Dist: autopep8
Requires-Dist: flake8
Requires-Dist: pytest
Requires-Dist: lightgbm
Requires-Dist: xgboost
Requires-Dist: catboost (>=0.17)
Requires-Dist: torch
Requires-Dist: ipython
Requires-Dist: dill
